README.md
setup.py
django_alexa2/__init__.py
django_alexa2.egg-info/PKG-INFO
django_alexa2.egg-info/SOURCES.txt
django_alexa2.egg-info/dependency_links.txt
django_alexa2.egg-info/requires.txt
django_alexa2.egg-info/top_level.txt