Metadata-Version: 1.1
Name: django-alexa2
Version: 0.0.1
Summary: A library 
Home-page: https://github.com/atuchak/django-alexa
Author: Anton Tuchak
Author-email: anton.tuchak@gmail.com
License: UNKNOWN
Keywords: amazon alexa
Platform: UNKNOWN
Classifier: Intended Audience :: Developers
Classifier: Development Status :: 5 - Production/Stable
Classifier: Operating System :: OS Independent
Classifier: Programming Language :: Python :: 3
Classifier: Topic :: Internet :: WWW/HTTP
